libsedml/__init__.py
libsedml/_libsedml.cpython-310-i386-linux-gnu.so
python_libsedml-2.0.33.dist-info/METADATA
python_libsedml-2.0.33.dist-info/WHEEL
python_libsedml-2.0.33.dist-info/top_level.txt
python_libsedml-2.0.33.dist-info/RECORD
python_libsedml-2.0.33.dist-info/licenses/LICENSE.txt
