Metadata-Version: 2.4
Name: python-libsedml
Version: 2.0.33
Summary: LibSedML Python API
Home-page: https://github.com/fbergmann/libSEDML
Author: Frank T. Bergmann
Author-email: frank.bergmann@bioquant.uni-heidelberg.de
License: BSD
License-File: LICENSE.txt
Dynamic: author
Dynamic: author-email
Dynamic: description
Dynamic: home-page
Dynamic: license
Dynamic: license-file
Dynamic: summary
